pencil_pusher/__init__.py
pencil_pusher/__main__.py
pencil_pusher/documenter.py
pencil_pusher/file_util.py
pencil_pusher/github_api.py
pencil_pusher/process_util.py
pencil_pusher/repo_manager.py
pencil_pusher/configs/__init__.py
pencil_pusher/configs/base.py
pencil_pusher/configs/manager.py
pencil_pusher/configs/python_lang.py
pencil_pusher/configs/sidebar.py
pencil_pusher/configs/sources.py
pencil_pusher/configs/title_prefix.py
pencil_pusher/configs/title_suffix.py
pencil_pusher/configs/titles.py
tests/__init__.py
tests/test_action_config.py
tests/test_documenter.py
tests/test_file_util.py
tests/test_github_api.py
tests/test_repo_manager.py
tests/test_configs/__init__.py
tests/test_configs/config_helper.py
tests/test_configs/test_python.py
tests/test_configs/test_sidebar.py
tests/test_configs/test_sources.py
tests/test_configs/test_title_prefix.py
tests/test_configs/test_title_suffix.py
tests/test_configs/test_titles.py
pencil_pusher-1.6.1.dist-info/LICENSE
pencil_pusher-1.6.1.dist-info/METADATA
pencil_pusher-1.6.1.dist-info/WHEEL
pencil_pusher-1.6.1.dist-info/top_level.txt
pencil_pusher-1.6.1.dist-info/RECORD
